odoo10_addon_l10n_it_fatturapa-10.0.3.0.0-nspkg.pth
odoo/addons/l10n_it_fatturapa/README.rst
odoo/addons/l10n_it_fatturapa/__init__.py
odoo/addons/l10n_it_fatturapa/__manifest__.py
odoo/addons/l10n_it_fatturapa/bindings/README.md
odoo/addons/l10n_it_fatturapa/bindings/__init__.py
odoo/addons/l10n_it_fatturapa/bindings/_ds.diff
odoo/addons/l10n_it_fatturapa/bindings/_ds.py
odoo/addons/l10n_it_fatturapa/bindings/binding.diff
odoo/addons/l10n_it_fatturapa/bindings/binding.py
odoo/addons/l10n_it_fatturapa/bindings/donotapply.fatturapa.diff
odoo/addons/l10n_it_fatturapa/bindings/fatturapa.py
odoo/addons/l10n_it_fatturapa/bindings/xsd/Schema_del_file_xml_FatturaPA_versione_1.2.1.xsd
odoo/addons/l10n_it_fatturapa/controllers/__init__.py
odoo/addons/l10n_it_fatturapa/controllers/main.py
odoo/addons/l10n_it_fatturapa/data/FoglioStileAssoSoftware_v1.1.xsl
odoo/addons/l10n_it_fatturapa/data/fatturaordinaria_v1.2.1.xsl
odoo/addons/l10n_it_fatturapa/data/fatturapa_data.xml
odoo/addons/l10n_it_fatturapa/data/welfare.fund.type.csv
odoo/addons/l10n_it_fatturapa/demo/account_invoice_fatturapa.xml
odoo/addons/l10n_it_fatturapa/i18n/am.po
odoo/addons/l10n_it_fatturapa/i18n/ar.po
odoo/addons/l10n_it_fatturapa/i18n/bg.po
odoo/addons/l10n_it_fatturapa/i18n/bs.po
odoo/addons/l10n_it_fatturapa/i18n/ca.po
odoo/addons/l10n_it_fatturapa/i18n/cs.po
odoo/addons/l10n_it_fatturapa/i18n/da.po
odoo/addons/l10n_it_fatturapa/i18n/de.po
odoo/addons/l10n_it_fatturapa/i18n/el_GR.po
odoo/addons/l10n_it_fatturapa/i18n/en_GB.po
odoo/addons/l10n_it_fatturapa/i18n/es.po
odoo/addons/l10n_it_fatturapa/i18n/es_AR.po
odoo/addons/l10n_it_fatturapa/i18n/es_CL.po
odoo/addons/l10n_it_fatturapa/i18n/es_CO.po
odoo/addons/l10n_it_fatturapa/i18n/es_CR.po
odoo/addons/l10n_it_fatturapa/i18n/es_DO.po
odoo/addons/l10n_it_fatturapa/i18n/es_EC.po
odoo/addons/l10n_it_fatturapa/i18n/es_ES.po
odoo/addons/l10n_it_fatturapa/i18n/es_MX.po
odoo/addons/l10n_it_fatturapa/i18n/es_PE.po
odoo/addons/l10n_it_fatturapa/i18n/es_PY.po
odoo10_addon_l10n_it_fatturapa-10.0.3.0.0.dist-info/METADATA
odoo10_addon_l10n_it_fatturapa-10.0.3.0.0.dist-info/WHEEL
odoo10_addon_l10n_it_fatturapa-10.0.3.0.0.dist-info/namespace_packages.txt
odoo10_addon_l10n_it_fatturapa-10.0.3.0.0.dist-info/top_level.txt
odoo10_addon_l10n_it_fatturapa-10.0.3.0.0.dist-info/RECORD
